meshtagsplot.py
meshtagsplot-0.0.7.dist-info/METADATA
meshtagsplot-0.0.7.dist-info/WHEEL
meshtagsplot-0.0.7.dist-info/licenses/COPYING
meshtagsplot-0.0.7.dist-info/licenses/COPYING.lesser
meshtagsplot-0.0.7.dist-info/RECORD
