Metadata-Version: 2.4
Name: meshtagsplot
Version: 0.0.7
Summary: A convenience script using matplotlib to plot dolfinx mesh tags.
Project-URL: Homepage, https://gitlab.com/rbulle/tags_plot
Project-URL: Issues, https://gitlab.com/rbulle/tags_plot/-/issues
Author-email: Raphaël Bulle <raphael.bulle@inria.fr>
Maintainer-email: Raphaël Bulle <raphael.bulle@inria.fr>
License-Expression: GPL-3.0
License-File: COPYING
License-File: COPYING.lesser
Classifier: Operating System :: OS Independent
Classifier: Programming Language :: Python :: 3
Requires-Python: >=3.12
Requires-Dist: matplotlib
